<?xml version="1.0" encoding="utf-8" ?>
<Datatable xmlns:xsi="http://www.w3.org/2001/XMLSchema-instance" xmlns:xsd="http://www.w3.org/2001/XMLSchema" xsi:noNamespaceSchemaLocation="../Schemas/EmpireImprovementDefinition.xsd">
  <!-- Ship Hulls -->
  <EmpireImprovementDefinition Name="EmpireImprovementSlotsSmall01Mavros" Category="CategoryHullUpgrade" SubCategory="SubCategoryHullMilitary">
    <TechnologyPrerequisite>TechnologyImproveHull1Mavros</TechnologyPrerequisite>
    <SimulationDescriptorReference Name="EmpireImprovementSlotsSmall01Mavros" />
  </EmpireImprovementDefinition>

  <EmpireImprovementDefinition Name="EmpireImprovementSlotsSmall02Mavros" Category="CategoryHullUpgrade"  SubCategory="SubCategoryHullMilitary">
    <TechnologyPrerequisite>TechnologyImproveHull2Mavros</TechnologyPrerequisite>
    <SimulationDescriptorReference Name="EmpireImprovementSlotsSmall02Mavros" />
  </EmpireImprovementDefinition>

  <EmpireImprovementDefinition Name="EmpireImprovementSlotsMedium01Mavros" Category="CategoryHullUpgrade" SubCategory="SubCategoryHullMilitary">
    <TechnologyPrerequisite>TechnologyImproveHull3Mavros</TechnologyPrerequisite>
    <SimulationDescriptorReference Name="EmpireImprovementSlotsMedium01Mavros" />
  </EmpireImprovementDefinition>
  <EmpireImprovementDefinition Name="EmpireImprovementSlotsMedium02Mavros" Category="CategoryHullUpgrade" SubCategory="SubCategoryHullMilitary">
    <TechnologyPrerequisite>TechnologyImproveHull4Mavros</TechnologyPrerequisite>
    <SimulationDescriptorReference Name="EmpireImprovementSlotsMedium02Mavros" />
  </EmpireImprovementDefinition>

  <EmpireImprovementDefinition Name="EmpireImprovementSlotsLarge01Mavros" Category="CategoryHullUpgrade" SubCategory="SubCategoryHullMilitary">
    <TechnologyPrerequisite>TechnologyImproveHull5Mavros</TechnologyPrerequisite>
    <SimulationDescriptorReference Name="EmpireImprovementSlotsLarge01Mavros" />
  </EmpireImprovementDefinition>

  <EmpireImprovementDefinition Name="EmpireImprovementSlotsSmall04Mavros" Category="CategoryHullUpgrade" SubCategory="SubCategoryHullMilitary">
    <TechnologyPrerequisite>TechnologyImproveExplorerHullMavros</TechnologyPrerequisite>
    <PathPrerequisite Flags="Prerequisite,Discard,UnlockAvailability,Faction,AffinityMajorMavros">ClassEmpire,AffinityMappingMajorMavros</PathPrerequisite>
    <SimulationDescriptorReference Name="EmpireImprovementSlotsSmall04Mavros" />
  </EmpireImprovementDefinition>

  <!-- Gameplay Affinity -->
  <EmpireImprovementDefinition Name="EmpireImprovementExpansionDisapproval2Mavros" Category="CategoryOverColonization" SubCategory="SubCategoryApproval">
    <PathPrerequisite       Inverted="false"    Flags="Prerequisite,Discard,UnlockAvailability,Faction,AffinityGameplayTechnologyMajorMavros">../ClassEmpire,AffinityGameplayMajorMavros</PathPrerequisite>
    <TechnologyPrerequisite>TechnologyApproval3Mavros</TechnologyPrerequisite>
    <SimulationDescriptorReference Name="EmpireImprovementExpansionDisapproval2" />
  </EmpireImprovementDefinition>
  
  <!-- ESG Compatibility -->
  <!-- Opulent Frontiers -->
  <EmpireImprovementDefinition Name="EmpireImprovementOutpostLuxDepositValue_NoOutposts" Category="CategoryRecipeImprovement" SubCategory="SubCategoryEmpire">
    <PathPrerequisite Flags="Prerequisite,Discard,UnlockAvailability,Faction" Inverted="false">../ClassEmpire,!AffinityGameplayCravers,!AffinityGameplayVenetians,!AffinityGameplayTerrans,!AffinityGameplayTimeLords,!AffinityGameplayMajorHisshos,!AffinityGameplayTemplars,!AffinityGameplaySophons,!AffinityGameplayHoratio,!AffinityGameplayMajorMavros</PathPrerequisite>
    <TechnologyPrerequisite>TechnologyDiplomacy2Common</TechnologyPrerequisite>
    <SimulationDescriptorReference Name="EmpireImprovementOutpostLuxDepositValue_NoOutposts" />
  </EmpireImprovementDefinition>
</Datatable>